nbsite/.version
nbsite/__init__.py
nbsite/__main__.py
nbsite/cmd.py
nbsite/ipystartup.py
nbsite/nbbuild.py
nbsite/paramdoc.py
nbsite/shared_conf.py
nbsite/util.py
nbsite/_shared_static/alert.css
nbsite/_shared_static/dataframe.css
nbsite/_shared_static/gallery.css
nbsite/_shared_static/holoviz-icon-white.svg
nbsite/_shared_static/hv-sidebar-dropdown.css
nbsite/_shared_static/mystnb.css
nbsite/_shared_static/nbsite.css
nbsite/_shared_static/notebook.css
nbsite/_shared_static/scroller.css
nbsite/_shared_static/js/goatcounter.js
nbsite/_shared_templates/copyright-last-updated.html
nbsite/_shared_templates/github-stars-button.html
nbsite/_shared_templates/hv-sidebar-dropdown.html
nbsite/_shared_templates/sidebar-nav-bs-alt.html
nbsite/analytics/__init__.py
nbsite/gallery/__init__.py
nbsite/gallery/gen.py
nbsite/gallery/thumbnailer.py
nbsite/nb_interactivity_warning/__init__.py
nbsite/pyodide/ServiceHandler.js
nbsite/pyodide/ServiceWorker.js
nbsite/pyodide/WebWorker.js
nbsite/pyodide/WorkerHandler.js
nbsite/pyodide/__init__.py
nbsite/pyodide/site.webmanifest
nbsite/pyodide/_static/run_cell.js
nbsite/pyodide/_static/runbutton.css
nbsite/templates/basic/README.md
nbsite/templates/basic/conf.py
nbsite/templates/basic/index.rst
nbsite/templates/holoviz/README.md
nbsite/templates/holoviz/about.rst
nbsite/templates/holoviz/conf.py
nbsite/templates/holoviz/index.rst
nbsite/tests/__init__.py
nbsite/tests/test_cmd.py
nbsite/tests/test_nbbuild.py
nbsite/tests/test_util.py
nbsite-0.8.7.data/scripts/nbsite_cleandisthtml.py
nbsite-0.8.7.data/scripts/nbsite_fix_links.py
nbsite-0.8.7.data/scripts/nbsite_from_tmplate.py
nbsite-0.8.7.data/scripts/nbsite_generate_modules.py
nbsite-0.8.7.data/scripts/nbsite_nbpagebuild.py
nbsite-0.8.7.dist-info/LICENSE.txt
nbsite-0.8.7.dist-info/METADATA
nbsite-0.8.7.dist-info/WHEEL
nbsite-0.8.7.dist-info/entry_points.txt
nbsite-0.8.7.dist-info/top_level.txt
nbsite-0.8.7.dist-info/RECORD
