Metadata-Version: 2.1
Name: nbsite
Version: 0.8.7
Summary: Build a tested, sphinx-based website from notebooks.
Home-page: https://nbsite.holoviz.org
Author: HoloViz developers
Author-email: developers@holoviz.org
Maintainer: HoloViz developers
Maintainer-email: developers@holoviz.org
License: BSD-3
Project-URL: Documentation, https://nbsite.holoviz.org/
Project-URL: Source Code, https://github.com/holoviz-dev/nbsite
Project-URL: Bug Tracker, https://github.com/holoviz-dev/nbsite/issues
Classifier: Development Status :: 3 - Alpha
Classifier: Programming Language :: Python :: 3
Classifier: Operating System :: OS Independent
Classifier: License :: OSI Approved :: BSD License
Classifier: Intended Audience :: Developers
Classifier: Natural Language :: English
Requires-Python: >=3.9
License-File: LICENSE.txt
Requires-Dist: param>=1.7.0
Requires-Dist: pyviz-comms
Requires-Dist: ipykernel
Requires-Dist: nbformat
Requires-Dist: nbconvert
Requires-Dist: jupyter-client
Requires-Dist: myst-nb>=1.1
Requires-Dist: sphinx-design
Requires-Dist: notebook
Requires-Dist: sphinx>=7
Requires-Dist: beautifulsoup4
Requires-Dist: jinja2
Requires-Dist: pillow
Requires-Dist: portalocker
Requires-Dist: pydata-sphinx-theme<0.16,>=0.15
Requires-Dist: myst-parser>=3
Requires-Dist: sphinx-copybutton
Requires-Dist: sphinxext-rediraffe
Provides-Extra: build
Requires-Dist: setuptools; extra == "build"
Requires-Dist: param>=1.6.1; extra == "build"
Provides-Extra: gallery
Requires-Dist: selenium; extra == "gallery"
Requires-Dist: phantomjs; extra == "gallery"
Provides-Extra: refman
Requires-Dist: graphviz; extra == "refman"
Provides-Extra: tests
Requires-Dist: flake8; extra == "tests"
Requires-Dist: pytest>=3.9.1; extra == "tests"
Requires-Dist: pre-commit; extra == "tests"
